qt_ble_discovery_widget/__init__.py
qt_ble_discovery_widget/main.py
qt_ble_discovery_widget/objects.py
qt_ble_discovery_widget-1.0.0.dist-info/METADATA
qt_ble_discovery_widget-1.0.0.dist-info/WHEEL
qt_ble_discovery_widget-1.0.0.dist-info/RECORD
