Metadata-Version: 2.4
Name: qt-ble-discovery-widget
Version: 1.0.0
Summary: A Qt widget for BLE device discovery
Author-email: floris vernieuwe <floris@vernieuwe.eu>
Requires-Python: >=3.10
Requires-Dist: bleak>=0.22.3
Requires-Dist: qt-custom-treewidget>=0.2.1
Requires-Dist: qtpy>=2.4.3
